{
    "biomes": {
        "arctic": {
            "primary_color": "#E6F7FF",
            "secondary_color": "#CCE6FF",
            "icon": "snowflake",
            "animals": [
                {
                    "name": "Polar Bear",
                    "svg_path": "assets/biome_data/arctic/polar_bear.svg"
                },
                {
                    "name": "Penguin",
                    "svg_path": "assets/biome_data/arctic/penguin.svg"
                },
                {
                    "name": "Snowy Owl",
                    "svg_path": "assets/biome_data/arctic/snowy_owl.svg"
                },
                {
                    "name": "Reindeer",
                    "svg_path": "assets/biome_data/arctic/reindeer.svg"
                }
            ]
        }
    }
}